README.md
setup.py
emmapy/__init__.py
emmapy/model.py
emmapy.egg-info/PKG-INFO
emmapy.egg-info/SOURCES.txt
emmapy.egg-info/dependency_links.txt
emmapy.egg-info/not-zip-safe
emmapy.egg-info/top_level.txt