Metadata-Version: 1.0
Name: emmapy
Version: 0.1.1
Summary: Python simple SMTP E-mail module
Home-page: http://github.com/phenicle/emmapy
Author: Phenicle Beefheart
Author-email: pheniclebeefheart@gmail.com
License: Apache 2.0
Platform: UNKNOWN
